{ "debtor":"francis bafra mayanja",
    "invoiceNumber":456353,
   " debtorsAddress":{
        "street":"Kampala Rd",
                 "city":"Makindye",
                  "postalAddress":"fdg45",
                  "country":"Uganda'"    },
    "issuingDate":"Thu Mar 27 2022 16:55:42 GMT+0300",
    "status":"pending",
    " description":"Re-branding", 

    "terms":7,
    "issuingAddress":{
    "street":"19 Mobutu Roard",
    
   " country":"Uganda", "postalAddress":"411", "city":"Kampala" 
   
},
"paymentDate":"21 Jan 2022",
"email":"bafra@gmail.com",
"items":[
 
   

    { "qty":4, "price":41, "name": "iik" },
    {" qty":13, "price":1, "name": "jjj"},
    { "qty":7, "price":40, "name": "eggs" },
    { "qty":20, "price":911, "name": "eggs" },
    {" qty":13, "price":1, "name": "jjj"},
    { "qty":7, "price":40, "name": "eggs" },
    { "qty":20, "price":911, "name": "eggs" }
   
]
}